cloudimage/URLBuilder.py
cloudimage/__init__.py
cloudimage/constants.py
cloudimage/exceptions.py
cloudimage/lib/__init__.py
cloudimage/lib/base.py
cloudimage/lib/v6.py
cloudimage/lib/v7.py
tests/__init__.py
cloudimage-0.0.1.dist-info/LICENSE
cloudimage-0.0.1.dist-info/METADATA
cloudimage-0.0.1.dist-info/WHEEL
cloudimage-0.0.1.dist-info/top_level.txt
cloudimage-0.0.1.dist-info/RECORD
