Metadata-Version: 2.1
Name: cloudimage
Version: 0.0.1
Summary: Cloudimage python library
Home-page: https://www.cloudimage.io
Author: Scaleflex SAS
Author-email: hello@scaleflex.com
License: UNKNOWN
Platform: UNKNOWN
Classifier: Programming Language :: Python :: 3
Classifier: License :: OSI Approved :: MIT License
Classifier: Operating System :: OS Independent
Requires-Python: >=3.6
